rl_cli/__init__.py
rl_cli/main.py
rl_cli/net.py
rl_cli/utils.py
rl_cli/commands/__init__.py
rl_cli/commands/blueprint.py
rl_cli/commands/devbox.py
rl_cli/commands/object.py
rl_cli-0.2.26.dist-info/entry_points.txt
rl_cli-0.2.26.dist-info/licenses/LICENSE
rl_cli-0.2.26.dist-info/WHEEL
rl_cli-0.2.26.dist-info/METADATA
rl_cli-0.2.26.dist-info/RECORD
