Metadata-Version: 2.4
Name: rl_cli
Version: 0.2.26
Summary: Runloop CLI for interacting with the Runloop APIs.
Author-email: Runloop AI <eng+cli@runloop.ai>
Requires-Python: >=3.12
Classifier: License :: OSI Approved :: MIT License
License-File: LICENSE
Requires-Dist: runloop-api-client==0.64.0
Requires-Dist: aiohttp>=3.9.0
Requires-Dist: tabulate>=0.9.0
Requires-Dist: zstandard>=0.22.0
Requires-Dist: python-dotenv>=1.0.0
Requires-Dist: flit ; extra == "dev"
Requires-Dist: pip-tools ; extra == "dev"
Requires-Dist: pytest ; extra == "dev"
Requires-Dist: pytest-asyncio>=0.23.0 ; extra == "dev"
Requires-Dist: pytest-timeout ; extra == "dev"
Requires-Dist: pytest-cov ; extra == "dev"
Requires-Dist: pytest-xdist ; extra == "dev"
Requires-Dist: pytest-sugar ; extra == "dev"
Requires-Dist: ruff ; extra == "dev"
Project-URL: Documentation, https://docs.runloop.ai
Project-URL: Home, https://www.runloop.ai
Project-URL: Source, https://github.com/runloopai/rl-cli
Provides-Extra: dev
